cuatro/__init__.py
cuatro/functions.py
cuatro/utilities.py
cuatro/demos/run_PLS.py
cuatro/demos/run_TIP.py
cuatro/demos/run_TIP_priors.py
cuatro/demos/run_TIS.py
cuatro/demos/run_TIS_priors.py
cuatro/demos/run_priors.py
cuatro/minimise_methods/minimise.py
cuatro/optimizer/CUATRO_optimizer_use.py
cuatro/optimizer/implementations/CUATRO_base.py
cuatro/optimizer/implementations/CUATRO_g.py
cuatro/optimizer/implementations/dim_red_heuristics/CUATRO_PLS.py
cuatro/optimizer/implementations/dim_red_heuristics/CUATRO_PLS_bandit.py
cuatro/optimizer/implementations/dim_red_heuristics/CUATRO_PLS_explore.py
cuatro/optimizer/implementations/dim_red_heuristics/CUATRO_embedding.py
cuatro/optimizer/implementations/global_heuristics/CUATRO_TIP.py
cuatro/optimizer/implementations/global_heuristics/CUATRO_TIS.py
cuatro/optimizer/implementations/local_heuristics/CUATRO_exploit_explore.py
cuatro/optimizer/implementations/local_heuristics/CUATRO_feasible_sampling.py
cuatro/optimizer/implementations/local_heuristics/CUATRO_sampling_region.py
cuatro/samplers/sampling.py
cuatro/test_functions/constraints/rosenbrock_constrained.py
cuatro/test_functions/functions/benchmarking_funcs.py
cuatro/test_functions/high_dim/RB.py
cuatro-0.1.3.dist-info/LICENSE.txt
cuatro-0.1.3.dist-info/METADATA
cuatro-0.1.3.dist-info/WHEEL
cuatro-0.1.3.dist-info/top_level.txt
cuatro-0.1.3.dist-info/RECORD
