Metadata-Version: 2.1
Name: cuatro
Version: 0.1.3
Summary: Convex qUAdratic Trust Region Optimizer.
Author-email: Damien van de Berg <dv516@ic.ac.uk>
Project-URL: Repository, https://github.com/OptiMaL-PSE-Lab/cuatro
Keywords: black-box optimization,high-dimensional,constraint satisfaction
Classifier: Development Status :: 3 - Alpha
Classifier: Intended Audience :: Developers
Classifier: Intended Audience :: Information Technology
Classifier: Intended Audience :: Science/Research
Classifier: License :: OSI Approved :: MIT License
Classifier: Natural Language :: English
Classifier: Programming Language :: Python :: 3
Classifier: Topic :: Scientific/Engineering :: Information Analysis
Classifier: Topic :: Scientific/Engineering :: Mathematics
Requires-Python: >=3.10
License-File: LICENSE.txt
Requires-Dist: matplotlib
Requires-Dist: numpy
Requires-Dist: scipy
Requires-Dist: cvxpy
Requires-Dist: scikit-learn
Provides-Extra: optional
Requires-Dist: gurobi ; extra == 'optional'
Requires-Dist: mosek ; extra == 'optional'
